cloudrail/terraform_0_15/__init__.py
cloudrail/terraform_0_15/terraform
cloudrail_terraform_0_15-0.15.0.dist-info/METADATA
cloudrail_terraform_0_15-0.15.0.dist-info/WHEEL
cloudrail_terraform_0_15-0.15.0.dist-info/top_level.txt
cloudrail_terraform_0_15-0.15.0.dist-info/RECORD
