Metadata-Version: 2.1
Name: cloudrail-terraform-0-15
Version: 0.15.0
Summary: CloudRail custom terraform binary 0.15
Home-page: UNKNOWN
Author: Indeni
License: UNKNOWN
Platform: UNKNOWN
Requires-Python: >=3.6, <4
